clickshot/__init__.py
clickshot/config.py
clickshot/element.py
clickshot/exceptions.py
clickshot/image.py
clickshot/keyboard.py
clickshot/locater.py
clickshot/matchers.py
clickshot/mouse.py
clickshot/region.py
clickshot/screen_grabber.py
clickshot-0.4.0.dist-info/WHEEL
clickshot-0.4.0.dist-info/METADATA
clickshot-0.4.0.dist-info/RECORD
